SpectraFP/__init__.py
SpectraFP/__main__.py
SpectraFP/fastsimilarity.py
SpectraFP/spectrafp.py
SpectraFP/data/df_l0.pkl
SpectraFP/data/df_l1.pkl
SpectraFP/data/df_l2.pkl
SpectraFP/data/df_l3.pkl
SpectraFP/data/df_l4.pkl
SpectraFP/data/metabolites.pkl
SpectraFP/data/multiplicities.csv
SpectraFP-1.2.5.dist-info/LICENSE
SpectraFP-1.2.5.dist-info/METADATA
SpectraFP-1.2.5.dist-info/WHEEL
SpectraFP-1.2.5.dist-info/top_level.txt
SpectraFP-1.2.5.dist-info/RECORD
