Metadata-Version: 2.1
Name: SpectraFP
Version: 1.2.5
Summary: A package to perform fingerprints from spectroscopy datas.
Home-page: https://github.com/jeffrichardchemistry/SpectraFP
Author: Jefferson Richard
Author-email: jrichardquimica@gmail.com
License: GNU GPL
Keywords: Cheminformatics,Chemistry,QSAR,QSPR,Fingerprint,Spectroscopy
Classifier: Intended Audience :: Developers
Classifier: Intended Audience :: Science/Research
Classifier: Topic :: Scientific/Engineering :: Chemistry
Classifier: Topic :: Scientific/Engineering :: Physics
Classifier: Topic :: Scientific/Engineering :: Bio-Informatics
Classifier: Topic :: Scientific/Engineering
Classifier: License :: OSI Approved :: GNU General Public License v3 (GPLv3)
Classifier: Natural Language :: English
Classifier: Operating System :: Microsoft :: Windows
Classifier: Operating System :: POSIX :: Linux
Classifier: Environment :: MacOS X
Classifier: Programming Language :: Python :: 3.8
Classifier: Programming Language :: Python :: 3.9
Classifier: Programming Language :: Python :: 3.10
License-File: LICENSE
Requires-Dist: pandas<=2.0.3
Requires-Dist: numpy<=1.24.4
Requires-Dist: tqdm
